pycad/COM.py
pycad/Logger.py
pycad/OnStart.py
pycad/SPI.py
pycad/__init__.py
pycad-0.0.0.1.dist-info/LICENSE
pycad-0.0.0.1.dist-info/METADATA
pycad-0.0.0.1.dist-info/WHEEL
pycad-0.0.0.1.dist-info/top_level.txt
pycad-0.0.0.1.dist-info/RECORD
