Metadata-Version: 2.1
Name: pycad
Version: 0.0.0.1
Summary: python lib raspberry
Home-page: https://github.com/CADindustries/
Author: Airat Abdrakov
Author-email: crackanddie@gmail.com
License: MIT
Download-URL: https://github.com/CADindustries/
Keywords: pycad,studicad,raspberrypi
Platform: UNKNOWN
Classifier: Development Status :: 3 - Alpha
Classifier: Intended Audience :: Developers
Classifier: Topic :: Software Development :: Build Tools
Classifier: License :: OSI Approved :: MIT License
Classifier: Programming Language :: Python :: 3.7
Classifier: Programming Language :: Python :: 3.8
License-File: LICENSE
